README.rst
setup.py
idl_parser/__init__.py
idl_parser/const.py
idl_parser/enum.py
idl_parser/exception.py
idl_parser/interface.py
idl_parser/module.py
idl_parser/node.py
idl_parser/parser.py
idl_parser/struct.py
idl_parser/token_buffer.py
idl_parser/type.py
idl_parser/typedef.py
idl_parser/union.py
idl_parser.egg-info/PKG-INFO
idl_parser.egg-info/SOURCES.txt
idl_parser.egg-info/dependency_links.txt
idl_parser.egg-info/top_level.txt