Metadata-Version: 1.1
Name: idl-parser
Version: 0.0.15
Summary: Very simple OMG IDL (Interface Definition Language) parser. This parses IDL files and outputs intermediate class objects.
Home-page: http://www.sugarsweetrobotics.com/
Author: ysuga
Author-email: ysuga@ysuga.net
License: GPLv3
Download-URL: https://github.com/sugarsweetrobotics/idl_parser
Platform: UNKNOWN
Classifier: Development Status :: 5 - Production/Stable
Classifier: Environment :: Console
Classifier: Intended Audience :: Developers
Classifier: License :: OSI Approved :: GNU General Public License v3 (GPLv3)
Classifier: Natural Language :: English
Classifier: Operating System :: OS Independent
Classifier: Programming Language :: Python
Classifier: Topic :: Scientific/Engineering
